nyxbox/main.py
nyxbox/styles.tcss
nyxbox/webapp.py
nyxbox/language-support/highlights-cpp.scm
nyxbox/plugins/__init__.py
nyxbox/plugins/auth_utils.py
nyxbox/plugins/challenge_loader.py
nyxbox/plugins/challenge_view.py
nyxbox/plugins/editor_tools.py
nyxbox/plugins/utils.py
nyxbox/plugins/code_runners/c_runner.py
nyxbox/plugins/code_runners/cpp_runner.py
nyxbox/plugins/code_runners/java_runner.py
nyxbox/plugins/code_runners/js_runner.py
nyxbox/plugins/code_runners/py_runner.py
nyxbox-1.0.3.dist-info/licenses/LICENSE
nyxbox-1.0.3.dist-info/METADATA
nyxbox-1.0.3.dist-info/WHEEL
nyxbox-1.0.3.dist-info/entry_points.txt
nyxbox-1.0.3.dist-info/top_level.txt
nyxbox-1.0.3.dist-info/RECORD
