Metadata-Version: 2.4
Name: NyxBox
Version: 1.0.3
Summary: LeetCode inspired app in your terminal, powered with Python and built on Textual!
Author-email: Rainger <tilt-hazard-swept@duck.com>
Project-URL: main page, https://nyxbox.thisisrainy.hackclub.app
Project-URL: github, https://github.com/thisiscid/NyxBox
Requires-Python: <3.13,>=3.10
License-File: LICENSE
Requires-Dist: textual>=3.2.0
Requires-Dist: tree-sitter>=0.24.0
Requires-Dist: tree-sitter-languages>=1.10.2
Requires-Dist: tree-sitter-cpp>=0.23.4
Requires-Dist: tree-sitter-javascript>=0.23.1
Requires-Dist: tree-sitter-python>=0.23.6
Requires-Dist: tree-sitter-java>=0.23.5
Requires-Dist: typing-extensions>=4.12.2
Requires-Dist: textual[syntax]
Requires-Dist: qrcode
Requires-Dist: rich-pixels
Requires-Dist: pillow
Requires-Dist: requests
Requires-Dist: httpx
Dynamic: license-file
